tinder_endpoints/__init__.py
tinder_endpoints-0.1.3.dist-info/LICENSE
tinder_endpoints-0.1.3.dist-info/METADATA
tinder_endpoints-0.1.3.dist-info/WHEEL
tinder_endpoints-0.1.3.dist-info/top_level.txt
tinder_endpoints-0.1.3.dist-info/RECORD
