Metadata-Version: 2.1
Name: tinder-endpoints
Version: 0.1.3
Summary: Tinder's API endpoints
Home-page: https://gitlab.com/velvetkeyboad/py-tinder-endpoints
Author: Ramon Moraes
Author-email: ramonmoraes8080@gmail.com
License: MIT
Platform: UNKNOWN
Classifier: Development Status :: 4 - Beta
Classifier: License :: OSI Approved :: MIT License
Classifier: Programming Language :: Python
Classifier: Programming Language :: Python :: 3
Classifier: Programming Language :: Python :: 3.6
Classifier: Programming Language :: Python :: 3.7
Classifier: Programming Language :: Python :: 3.8
Requires-Dist: endpoints-mapper (==0.3.0)
